{
    "amount_likes": 0,
    "amount_published": 0,
    "amount_shares": {
        "bz": 0,
        "fb": 0,
        "tw": 0
    },
    "amount_sources": 0,
    "amount_visits": 2370,
    "author": {
        "fullname": "أسماء الغول",
        "id": "5e209f94d4a22920b844f063",
        "photo": {
            "path": "authors/1579955610_asmaa11111.jpg"
        }
    },
    "caption": " كل ما ينسب له مؤخراً من تصريحات لا يمت للحقيقة بصلة (Facebook)",
    "category": "Arts & Culture",
    "claim": "<p dir=\"RTL\" style=\"text-align:justify\">حسابات على وسائل التواصل الاجتماعي تعود إلى الممثل عمرو عبد الجليل وتغرد حول مسلسل &quot;النهاية&quot;</p>\r\n",
    "country": "EG",
    "created_at": "2020-05-03 15:13:24",
    "created_by": "5d921f5fbe494b2d75391892",
    "deleted_at": null,
    "feature": 0,
    "feedback_neg": 0,
    "feedback_pos": 0,
    "id": "5eaeb564db291609e7441205",
    "investigation": "<p dir=\"RTL\" style=\"text-align:justify\">وجد &quot;مسبار&quot; مقطع فيديو نشره الممثل يوسف الشريف على حسابه الموثَّق في &quot;فيسبوك&quot; بالنيابة عن عمرو عبد الجليل، في الثاني من مايو/ أيار الجاري،&nbsp;نفى فيه امتلاكه أيّة حسابات على وسائل التواصل الاجتماعيّ، ومؤكّداً أنّ كل ما ينسب له مؤخراً لا يمت للحقيقة بصلة، وواصفاً ما نسب إليه من تصريحات بأنّه &quot;عك&quot;، كما وعد جمهوره بأنّه سيبلغهم حين يقوم بإنشاء حسابات على وسائل التواصل الاجتماعيّ.</p>\r\n\r\n<p style=\"text-align:center\"><img src=\"https://images-prod.misbar.com/articlebody/investigation_2sw4diymx.jpg\" style=\"height:289px; width:605px\" /></p>\r\n",
    "is_deleted": false,
    "is_published": true,
    "is_top_eligible": true,
    "keywords": [
        ""
    ],
    "last_comments": [],
    "last_edited_at": null,
    "names": [],
    "origin": "<p dir=\"RTL\" style=\"text-align:justify\">تداول مئاتٌ من مستخدمي وسائل التوصل الاجتماعيّ تغريداتٍ وتدويناتٍ من حساباتٍ نُسبت إلى الممثل المصريّ عمرو عبد الجليل على مواقع تويتر وانستغرام وفيسبوك، بل تصدَّر اسم الممثل ليكون تريند؛ وذلك بسبب دوره في مسلسل &quot;النهاية&quot; الذي يُعرض حالياً على الفضائيّات العربيّة من بطولة الممثل يوسف الشريف، ويلعب فيه الأخير دور &quot;روبوت&quot; يقوم بصنعه الريس عزيز الذي يؤدي دوره عبد الجليل. وأغلب التغريدات على حساباته جاءت ساخرة من دوره في المسلسل وردوده على الناس الذين يطلبون منه طريقة صناعة &quot;الروبوت&quot;، أما تغريدات المستخدمين في التريند فأغلبها يمتدح أداءه في الدور، ويعلّق على المسلسل.</p>\r\n\r\n<p dir=\"RTL\" style=\"text-align:justify\"><span style=\"background-color:white\">كما ردّ حساب الممثل على &quot;تويتر&quot; على المتحدث باسم الجيش الاسرائيليّ أفخاي أدرعي الذي انتقد مسلسل &quot;النهاية&quot; لأنّه يتحدث عن نهاية &quot;إسرائيل&quot;، بقوله:<span style=\"color:black\">&nbsp;&quot;أهم حاجة يا فيخو في النهاية إنّك تبقى فاهم وواعي وانت كده فعلا فاهم وواعي أن نهايتكم قربت..أ</span><span style=\"color:black\">بو تقل دم أمك ع الصبح</span><span dir=\"LTR\"><span style=\"color:black\">&quot;.</span></span></span></p>\r\n\r\n<p style=\"text-align:center\">&nbsp;</p>\r\n\r\n<p style=\"text-align:center\"><img src=\"https://images-prod.misbar.com/articlebody/origin_y9fm8vf0e.jpg\" style=\"height:248px; width:604px\" /></p>\r\n\r\n<p style=\"text-align:center\"><img src=\"https://images-prod.misbar.com/articlebody/origin_xox7ergfo.jpg\" style=\"height:405px; width:604px\" /><img src=\"https://images-prod.misbar.com/articlebody/origin_rl9bn64km.jpg\" style=\"height:270px; width:605px\" /></p>\r\n\r\n<p style=\"text-align:center\">&nbsp;</p>\r\n\r\n<p style=\"text-align:center\">&nbsp;</p>\r\n\r\n<p style=\"text-align:center\"><img src=\"https://images-prod.misbar.com/articlebody/origin_ntdlk0876.jpg\" style=\"height:201px; width:589px\" /><img src=\"https://images-prod.misbar.com/articlebody/origin_bhm6fwq0e.jpg\" style=\"height:217px; width:605px\" /></p>\r\n\r\n<p style=\"text-align:center\"><img src=\"https://images-prod.misbar.com/articlebody/origin_f68wkvw9i.jpg\" style=\"height:515px; width:605px\" /></p>\r\n\r\n<p style=\"text-align:center\"><img src=\"https://images-prod.misbar.com/articlebody/origin_kjnhavm7i.jpg\" style=\"height:565px; width:597px\" /></p>\r\n",
    "original_language": "Arabic",
    "photo": {
        "height": 244,
        "left": -5.77777099609375,
        "path": "articles/1588508004عععع.jpg",
        "top": 77.08984375,
        "totalHeight": 423,
        "totalWidth": 423,
        "watermark_path": "articles/watermark-1588508004عععع.jpg",
        "width": 433
    },
    "post_date": "2020-05-03T11:44:00.000+03:00",
    "published": [
        {
            "link": "https://www.facebook.com/AmrAbdelGelil1/?__tn__=%2Cd%2CP-R&eid=ARBGfJpuQ9be3FAKYVCGKFBhMSV1OP179MT0HejlrJqKPyEdBGe_zn7bL2m8DjNmv9VWwgnWKgouaF5L",
            "name": "عمرو عبد الجليل على فيسبوك",
            "path": "published/0_1588508003_عمرو تويتر.jpg"
        },
        {
            "link": "https://twitter.com/AmrOfficial3",
            "name": "عمرو عبد الجلبل على تويتر",
            "path": "published/1_1588508003_عمرو تويتر.jpg"
        },
        {
            "link": "https://www.instagram.com/amrabdelgelilofficial1/",
            "name": "عمرو عبد الجليل على انستغرام",
            "path": "published/2_1588508003_عمرو تويتر.jpg"
        },
        {
            "link": "https://arabic.rt.com/middle_east/1110049-%D9%81%D9%86%D8%A7%D9%86-%D9%85%D8%B5%D8%B1%D9%8A-%D9%8A%D9%88%D8%AC%D9%87-%D9%85%D8%AE%D8%A7%D8%B7%D8%A8%D8%A7-%D8%A3%D9%81%D9%8A%D8%AE%D8%A7%D9%8A-%D8%A3%D8%AF%D8%B1%D8%B9%D9%8A-%D9%86%D9%87%D8%A7%D9%8A%D8%AA%D9%83%D9%85-%D9%82%D8%B1%D8%A8%D8%AA/",
            "name": "روسيا اليوم",
            "path": "published/3_1588509010_ار تي روسيا.jpg"
        }
    ],
    "result": "false",
    "shared_articles_count": 0,
    "sources": [
        {
            "link": "https://www.facebook.com/egyfilm.Youssef.El.Sherif/videos/318329482484719/?v=318329482484719",
            "name": "يوسف الشريف",
            "path": "sources/0_1588508003_يوسف.jpg"
        }
    ],
    "stats": null,
    "subtitle": "",
    "title": "الممثل عمرو عبد الجليل لم يغرّد حول مسلسل النهاية",
    "updated_at": "2020-09-25 03:19:18",
    "url_path": "/factcheck/2020/05/03/الممثل-عمرو-عبد-الجليل-لم-يغرد-حول-مسلسل-النهاية"
}