{
    "amount_likes": 0,
    "amount_published": 0,
    "amount_shares": {
        "bz": 0,
        "fb": 0,
        "tw": 0
    },
    "amount_sources": 0,
    "amount_visits": 260,
    "author": {
        "fullname": "ุจูุงู ุญูุฏุงู",
        "id": "5fa0632609eb9442f11d9d69",
        "photo": {
            "name": "1604346662_2010.jpg",
            "path": "authors/1604346662_2010.jpg"
        }
    },
    "caption": "ููู ุงูุงุชุญุงุฏ ุตุญุฉ ุงูุจูุงู ุงููุชุฏุงูู (ุงููููุน ุงูุฑุณูู ููุงุชุญุงุฏ)",
    "category": "Politics",
    "claim": "<p dir=\"RTL\">ุงูุงุชุญุงุฏ ุงูุนุงููู ูุนููุงุก ุงููุณูููู ูุตุฏุฑ ุจูุงูุงู ูุฏูู ููู ุชุทุจูุน ุงูุนูุงูุงุช ุจูู ุงููุบุฑุจ ู ุงูููุงู ุงูุตููููู ูููุงุฌู ุฏููุฉ ุงูุฌุฒุงุฆุฑ.</p>\r\n",
    "country": "DZ",
    "created_at": "2020-12-14 21:41:12",
    "created_by": "5f9fab38bddeec3fc23209e0",
    "deleted_at": null,
    "feature": 0,
    "feedback_neg": 4,
    "feedback_pos": 7,
    "id": "5fd7b1c892d5654ba8533445",
    "investigation": "<p dir=\"rtl\">ุชุญูู &quot;<a href=\"https://misbar.com/qna\" target=\"_blank\">ูุณุจุงุฑ</a>&quot; ูู ุงูุตูุฑุฉ ูุงูุงุฏุนุงุก ุงููุชุฏุงูููู ููุฌุฏ ุฃูููุง ุฒุงุฆูุงูุ ุฅุฐ ุจูู ุงูุงุชุญุงุฏ ุงูุนุงููู ูุนููุงุก ุงููุณูููู ูู&nbsp;<a href=\"https://web.facebook.com/iumsonline/posts/3912377398795295\" target=\"_blank\">ููุดูุฑ</a>&nbsp;ุนูู ุตูุญุชู ุนูู &quot;ููุณุจูู&quot; ููู ุงูุณุจุช 12 ุฏูุณูุจุฑ ุงูุฌุงุฑูุ ุฃู ุงูุจูุงู ุงููุชุฏุงูู ุญุฏูุซุงู ููุจุฑูุงูุ ูุฃู &quot;ูู ูุง ุตุฏุฑ ุนู ุงูุงุชุญุงุฏ ูู ูุฐุง ุงููุฌุงู ูู ุฅุฏุงูุชู ูุชุทุจูุน ุงููุบุฑุจ ( ูุบูุฑู ) ูุน ุงููุญุชููู ููุฏุณูุง ูุฃุฑุถูุงุ ูููุณ ููู ุงู ุงุดุงุฑุฉ ููุฌุฒุงุฆุฑ ุฃู ุงูุตุญุฑุงุกุ ููุง ุณูู ุฐูู ููู ุงูุชุฑุงุก ุนูู ุงูุงุชุญุงุฏ&quot;ุ ูุดูุฑุงู ุฅูู&nbsp;<a href=\"https://www.iumsonline.org/ar/ContentDetails.aspx?ID=12821\" target=\"_blank\">ุงูุจูุงู</a>&nbsp;ุงูุฃุตูู ุงูุฐู ูุดุฑ ุนูู ูููุน ุงูุงุชุญุงุฏ ููู ุงูุฌูุนุฉ 11 ุฏูุณูุจุฑ ุงูุฌุงุฑู.</p>\r\n\r\n<p dir=\"rtl\"><iframe frameborder=\"0\" height=\"710\" scrolling=\"no\" src=\"https://www.facebook.com/plugins/post.php?href=https%3A%2F%2Fweb.facebook.com%2Fiumsonline%2Fposts%2F3912377398795295&amp;show_text=true&amp;width=553&amp;height=710&amp;appId\" style=\"border:none;overflow:hidden\" width=\"553\"></iframe></p>\r\n\r\n<p dir=\"RTL\">ููุถููุงู &quot;ุฃู ุงูุงุชุญุงุฏ ูุง ูููู ูุณุคููุงู ุฅูุง ุนูุง ูุตุฏุฑ ููู ุฑุณููุงู ุนูู ูุณุงู ุฑุฆูุณู ุฃูุฃูููู ุงูุนุงู&quot;ุ ูุฃุฑุฌุฃ ุณุจุจ ุงุชูุงู ุงูุงุชุญุงุฏ ุจููุงุฌูุฉ ุฏููุฉ ุงูุฌุฒุงุฆุฑ ุฅูู ููุงูุฉ ูุดุฑุช ุนูู ูููุน ุชุนุจุฑ ุนู ุฑุฃู ูุงุชุจูุงุ ูุฃูู ูุฏ ุชู ุญุฐููุง &nbsp;ูุฃููุง &quot;ูุง ุชุนุจุฑ ุนู ุฑุฃู ุงูุงุชุญุงุฏ&quot;.</p>\r\n\r\n<p dir=\"RTL\">ููุฃุชู ูุฐุง ุงูุงุฏุนุงุก ุนูุจ ุฏููุงูุฏ ุชุฑุงูุจุ ููู ุงูุฎููุณ 10 ุฏูุณูุจุฑ ุงูุฌุงุฑูุ ุชูููุนู ุฅุนูุงูุงู ูุนุชุฑู ุจุณูุงุฏุฉ ุงููุบุฑุจ ุนูู ููุทูุฉ ุงูุตุญุฑุงุก ุงูุบุฑุจูุฉ ุงููุชูุงุฒุน ุนูููุงุ ูุฑุนุงูุฉ ุชุทุจูุน ุงูุนูุงูุงุช ุจูู ุงููุบุฑุจ ูุงูููุงู ุงูุตููููู.</p>\r\n\r\n<blockquote class=\"twitter-tweet\">\r\n<p dir=\"ltr\">Today, I signed a proclamation recognizing Moroccan sovereignty over the Western Sahara. Morocco&#39;s serious, credible, and realistic autonomy proposal is the ONLY basis for a just and lasting solution for enduring peace and prosperity!</p>\r\n&mdash; Donald J. Trump (@realDonaldTrump) <a href=\"https://twitter.com/realDonaldTrump/status/1337067019385057290?ref_src=twsrc%5Etfw\">December 10, 2020</a></blockquote>\r\n\r\n<blockquote class=\"twitter-tweet\">\r\n<p dir=\"ltr\">Another HISTORIC breakthrough today! Our two GREAT friends Israel and the Kingdom of Morocco have agreed to full diplomatic relations &ndash; a massive breakthrough for peace in the Middle East!</p>\r\n&mdash; Donald J. Trump (@realDonaldTrump) <a href=\"https://twitter.com/realDonaldTrump/status/1337067073051238400?ref_src=twsrc%5Etfw\">December 10, 2020</a></blockquote>\r\n\r\n<p dir=\"RTL\">ุงูุฑุฃ/ู ุฃูุถุงู</p>\r\n\r\n<p dir=\"RTL\"><a href=\"https://misbar.com/factcheck/2020/12/13/%D9%84%D9%85-%D9%8A%D8%B5%D8%B1%D8%AD-%D8%A8%D8%A7%D9%8A%D8%AF%D9%86-%D8%A8%D8%B9%D8%AF%D9%85-%D8%A5%D9%84%D8%BA%D8%A7%D8%A1-%D8%A7%D8%B9%D8%AA%D8%B1%D8%A7%D9%81-%D8%A3%D9%85%D9%8A%D8%B1%D9%83%D8%A7-%D8%A8%D9%85%D8%BA%D8%B1%D8%A8%D9%8A%D8%A9-%D8%A7%D9%84%D8%B5%D8%AD%D8%B1%D8%A7%D8%A1-%D8%A3%D9%88-%D8%AD%D8%B0%D9%81-%D8%A7%D9%84%D8%AC%D8%B2%D8%A7%D8%A6%D8%B1-%D9%85%D9%86-%D8%A7%D9%84%D8%AE%D8%A7%D8%B1%D8%B7%D8%A9\" target=\"_blank\">ูู ููุตุฑุญ ุจุงูุฏู ุจุนุฏู ุฅูุบุงุก ุงุนุชุฑุงู ุฃููุฑูุง ุจูุบุฑุจูุฉ ุงูุตุญุฑุงุก ุฃู ุญุฐู ุงูุฌุฒุงุฆุฑ ูู ุงูุฎุงุฑุทุฉ</a></p>\r\n\r\n<p dir=\"RTL\"><a href=\"https://misbar.com/factcheck/2020/12/12/%D8%AA%D8%B5%D8%B1%D9%8A%D8%AD-%D9%85%D9%81%D8%A8%D8%B1%D9%83-%D9%84%D9%86%D8%A7%D8%A6%D8%A8%D8%A9-%D8%A8%D8%A7%D9%8A%D8%AF%D9%86-%D8%B9%D9%86-%D8%A5%D8%B9%D9%84%D8%A7%D9%86-%D8%AA%D8%B1%D8%A7%D9%85%D8%A8-%D8%A8%D8%B4%D8%A3%D9%86-%D8%A7%D9%84%D8%B5%D8%AD%D8%B1%D8%A7%D8%A1-%D8%A7%D9%84%D8%BA%D8%B1%D8%A8%D9%8A%D8%A9\" target=\"_blank\">ุชุตุฑูุญ ููุจุฑู ููุงูุงูุง ูุงุฑูุณ ุญูู ุฅุนูุงู ุชุฑุงูุจ ุจุดุฃู ุงูุตุญุฑุงุก ุงูุบุฑุจูุฉ</a></p>\r\n",
    "is_deleted": false,
    "is_newsletter": true,
    "is_notification_pushed": true,
    "is_published": true,
    "is_top_eligible": true,
    "keywords": [
        "ุจูุงู",
        "ุงูุงุชุญุงุฏ ุงูุนุงููู ูุนููุงุก ุงููุณูููู",
        "ุงูุฌุฒุงุฆุฑ",
        "ููุงุฌู"
    ],
    "last_comments": [],
    "last_edited_at": null,
    "names": [],
    "origin": "<p dir=\"RTL\">ุชุชุฏุงูู ุตูุญุงุช ูุญุณุงุจุงุช ุนูู ููุงูุน ุงูุชูุงุตู ุงูุงุฌุชูุงุนู ููุฐ ููู 11 ุฏูุณูุจุฑ/ูุงููู ุงูุฃูู ุงูุฌุงุฑูุ ุตูุฑุฉ ุงุฏุนุช ุฃููุง ุชุจูู ุจูุงูุงู ูู ุงูุงุชุญุงุฏ ุงูุนุงููู ูุนููุงุก ุงููุณูููู ูุฏูู ููู ุชุทุจูุน ุงูุนูุงูุงุช ุจูู ุฏููุฉ ุงููุบุฑุจ ูุงูููุงู ุงูุตููููู ูููุงุฌู ุฏููุฉ ุงูุฌุฒุงุฆุฑ ุจุงุนุชุจุงุฑูุง-ุจุญุณุจ ุงูุงุฏุนุงุก- ุงูุณุจุจ ูู ุงูุชุทุจูุน.</p>\r\n\r\n<p dir=\"RTL\"><img alt=\"Text, letter\r\n\r\nDescription automatically generated\" src=\"https://images-prod.misbar.com/articlebody/origin_82917vzwk.jpg\" /></p>\r\n",
    "original_language": "Arabic",
    "photo": {
        "height": 423,
        "left": 0.5333251953125,
        "path": "articles/1607971271ุงุนู.PNG",
        "top": 0,
        "totalHeight": 423,
        "totalWidth": 752,
        "watermark_path": "articles/watermark-1607971271ุงุนู.PNG",
        "width": 752
    },
    "post_date": "2020-12-13T20:04:00.000+03:00",
    "published": [
        {
            "id": "5fd7b348e578fb558d0c10f4",
            "link": "https://twitter.com/FeredoMadjid/status/1337799428472791040",
            "name": "Feredo Madjid",
            "origin": "twitter",
            "path": "sources/b72dfbb95fce5f35c1df018bac3fba508ea2b1e6.jpg"
        },
        {
            "id": "5fd7b3487cd290462f50f84d",
            "link": "https://www.facebook.com/salafiusyoucef/photos/a.511910359158982/1335472463469430/?_rdc=1&_rdr",
            "name": "ููุงุฉ ุงูุฑุฏ ุนูู ุงููุฎุงูู",
            "origin": "facebook",
            "path": "sources/a9200bec23de3113ec2dd59164e8619459373d79.jpg"
        },
        {
            "id": "5fd7b3481a328a5f9f4077c7",
            "link": "https://twitter.com/Dido_Walid31/status/1337397548793917444",
            "name": "ูููุฏ Walid โฆโฆ๐ฉ๐ฟโฉ",
            "origin": "twitter",
            "path": "sources/893b46b44ce0ef20f488f9c8fa131a0672e15fae.jpg"
        },
        {
            "id": "5fd7b348784da64ef71f92ae",
            "link": "https://www.facebook.com/groups/730430040407667/permalink/3486368644813779/",
            "name": "algerie  democratique",
            "origin": "facebook",
            "path": "sources/9fb41797f3ab0b7b87f8775614ed7b0bdd915b9b.jpg"
        },
        {
            "id": "5fd7b34987e85310e565cbcf",
            "link": "https://www.facebook.com/so9orDz/posts/114767953810771",
            "name": "ุตููุฑ ุงูููุงููุฉ ุงูุฌุฒุงุฆุฑูุฉ",
            "origin": "facebook",
            "path": "sources/6b3340797d662ad0b16025f77177242881003287.jpg"
        }
    ],
    "result": "false",
    "shared_articles_count": 0,
    "sources": [
        {
            "id": "5f8e9c144a475921f425209d",
            "link": "https://www.iumsonline.org/ar/ContentDetails.aspx?ID=12821",
            "name": "ุงูุงุชุญุงุฏ ุงูุนุงููู ูุนููุงุก ุงููุณูููู",
            "origin": null,
            "path": "sources/ee9e8c8fee5e1913f188748e42b3791eb0a2dc9c.jpg"
        },
        {
            "id": "5faae9a3eb65480410630895",
            "link": "https://web.facebook.com/iumsonline/posts/3912377398795295?_rdc=1&_rdr",
            "name": "Ali Harizi",
            "origin": "",
            "path": "sources/af6f8f22c296a2f707be1985c48b9d0009cfa471.jpg"
        },
        {
            "id": "5fbfd52fa9883a30ff17ec63",
            "link": "https://twitter.com/realDonaldTrump/status/1337067019385057290",
            "name": "Donald J. Trump",
            "origin": "twitter",
            "path": "sources/6931b59ed1e7f521f4ef34a30aebfdb49b56c148.jpg"
        },
        {
            "id": "5fbfd52fa9883a30ff17ec63",
            "link": "https://twitter.com/realDonaldTrump/status/1337067073051238400",
            "name": "Donald J. Trump",
            "origin": "twitter",
            "path": "sources/6931b59ed1e7f521f4ef34a30aebfdb49b56c148.jpg"
        }
    ],
    "stats": null,
    "subtitle": "",
    "title": "ูู ูุตุฏุฑ ุงูุงุชุญุงุฏ ุงูุนุงููู ูุนููุงุก ุงููุณูููู ุจูุงูุงู ููุงุฌู ููู ุงูุฌุฒุงุฆุฑ",
    "updated_at": "2020-12-14 23:37:30",
    "url_path": "/factcheck/2020/12/14/ูู-ูุตุฏุฑ-ุงูุงุชุญุงุฏ-ุงูุนุงููู-ูุนููุงุก-ุงููุณูููู-ุจูุงูุง-ููุงุฌู-ููู-ุงูุฌุฒุงุฆุฑ",
    "was_notification_pushed": "true"
}