{
    "amount_likes": 0,
    "amount_published": 0,
    "amount_shares": {
        "bz": 0,
        "fb": 0,
        "tw": 0
    },
    "amount_sources": 0,
    "amount_visits": 367,
    "author": {
        "fullname": "بيان حمدان",
        "id": "5fa0632609eb9442f11d9d69",
        "photo": {
            "name": "1604346662_2010.jpg",
            "path": "authors/1604346662_2010.jpg"
        }
    },
    "caption": "فيديو قديم نشر عام 2017 (مواقع التواصل الاجتماعي)",
    "category": "Politics",
    "claim": "<p dir=\"RTL\" style=\"text-align:right\">مقطع فيديو يظهر معدات عسكرية للجيش المغربي&nbsp;من دبابات ومدرعات في منطقة الكركرات.</p>\r\n",
    "country": "MA",
    "created_at": "2020-11-30 15:39:58",
    "created_by": "5f9fab38bddeec3fc23209e0",
    "deleted_at": null,
    "feature": 0,
    "feedback_neg": 4,
    "feedback_pos": 6,
    "id": "5fc4e81e891411723f1b40a1",
    "investigation": "<p dir=\"RTL\" style=\"text-align:right\">تحقق &quot;<a href=\"https://misbar.com/qna\" style=\"color:#0563c1; text-decoration:underline\" target=\"_blank\">مسبار</a>&quot; من المقطع المتداول ووجد أنه مضلل، فبعد تقطيع الفيديو إلى صور واستخدامها في البحث العكسي، تبين أن <a href=\"https://www.youtube.com/watch?v=5hcVRpYCops\" style=\"color:#0563c1; text-decoration:underline\" target=\"_blank\">المقطع قديم</a> ونشر لأول مرة في أبريل/نيسان عام 2017، وادعى ناشروه أنه تم رصده في ولاية كولورادو الأميركية. وبمراجعة الفيديو الأصلي، فإن الثواني العشرين الأولى تظهر أن القطار يعود لشركة شحن أميركية &nbsp;تدعى <a href=\"https://www.up.com/aboutup/corporate_info/uprrover/index.htm\" style=\"color:#0563c1; text-decoration:underline\" target=\"_blank\">Union Pacific</a>، تعمل في 23 ولاية غرب الولايات المتحدة، ما يؤكد أن المقطع التقط داخل حدود الولايات الأميركية. &nbsp;كما يظهر صوت الشخص الذي التقط المقطع في الدقيقة 2:24، معلقاً على الآليات العسكرية باللغة الإنجليزية، وهذا ما تم حذفه في المقطع المتداول، إذ تم اقتصاص أول 20 ثانية، وتركيب موسيقى لإخفاء الأصوات الحقيقية الظاهرة في المقطع الأصلي.</p>\r\n\r\n<p dir=\"rtl\"><iframe frameborder=\"0\" height=\"315\" src=\"https://www.youtube.com/embed/5hcVRpYCops?start=28\" width=\"560\"></iframe></p>\r\n\r\n<p dir=\"rtl\">ويذكر أن منطقة الصحراء الغربية تشهد توترات عسكرية بين الجيش المغربي وقوات جبهة البوليساريو&nbsp;منذ 13 نوفمبر الجاري، بسبب قيام القوات المسلحة المغربية ببناء جدار أمني عند&nbsp;معبر الكركرات الحدودي، الأمر الذي اعتبرته الجبهة خرقاً لوقف إطلاق النار المتفق عليه، والذي استمر لثلاثة عقود.</p>\r\n\r\n<p dir=\"RTL\" style=\"text-align:right\">&nbsp;</p>\r\n\r\n<p dir=\"RTL\" style=\"text-align:right\">اقرأ/ي أيضاً</p>\r\n\r\n<p dir=\"RTL\" style=\"text-align:right\"><a href=\"https://misbar.com/editorial/2020/11/28/%D8%A3%D8%A8%D8%B1%D8%B2-%D8%A7%D9%84%D8%A3%D8%AE%D8%A8%D8%A7%D8%B1-%D8%A7%D9%84%D8%B2%D8%A7%D8%A6%D9%81%D8%A9-%D8%AD%D9%88%D9%84-%D8%A7%D9%84%D9%85%D9%88%D8%A7%D8%AC%D9%87%D8%A7%D8%AA-%D8%A8%D9%8A%D9%86-%D8%A7%D9%84%D9%85%D8%BA%D8%B1%D8%A8-%D9%88%D8%AC%D8%A8%D9%87%D8%A9-%D8%A7%D9%84%D8%A8%D9%88%D9%84%D9%8A%D8%B3%D8%A7%D8%B1%D9%8A%D9%88\" style=\"color:#0563c1; text-decoration:underline\" target=\"_blank\">أبرز الأخبار الزائفة حول المواجهات الأخيرة بين المغرب وجبهة البوليساريو</a></p>\r\n\r\n<p dir=\"rtl\"><a href=\"https://misbar.com/factcheck/2020/11/28/%D8%B5%D9%88%D8%B1%D8%A9-%D9%85%D9%81%D8%A8%D8%B1%D9%83%D8%A9-%D9%88%D9%84%D9%8A%D8%B3%D8%AA-%D9%84%D8%B3%D9%81%D8%A7%D8%B1%D8%A9-%D8%A7%D9%84%D8%AC%D8%B2%D8%A7%D8%A6%D8%B1-%D9%81%D9%8A-%D8%AA%D9%86%D8%AF%D9%88%D9%81\" style=\"color:#0563c1; text-decoration:underline\" target=\"_blank\">صورة مفبركة وليست لسفارة الجزائر في تندوف</a></p>\r\n",
    "is_deleted": false,
    "is_newsletter": true,
    "is_notification_pushed": true,
    "is_published": true,
    "is_top_eligible": true,
    "keywords": [
        ""
    ],
    "last_comments": [],
    "last_edited_at": null,
    "names": [],
    "origin": "<p dir=\"RTL\" style=\"text-align:right\">تداولت صفحات وحسابات على مواقع التواصل الاجتماعي، حديثاً ومنذ 21 نوفمبر/تشرين الثاني الجاري، مقطع فيديو يظهر آليات عسكرية منقولة على قطار، ادعت أنها تعود للجيش المغربي&nbsp;متوجهةً&nbsp;إلى معبر الكركرات.</p>\r\n\r\n<p dir=\"RTL\" style=\"text-align:right\"><span dir=\"LTR\"><img src=\"https://images-prod.misbar.com/articlebody/origin_6ay3vlsg7.jpg\" style=\"height:404px; width:513px\" /></span></p>\r\n",
    "original_language": "Arabic",
    "photo": {
        "height": 421,
        "left": 1.20001220703125,
        "path": "articles/1606739996مر.PNG",
        "top": 0.956298828125,
        "totalHeight": 423,
        "totalWidth": 752,
        "watermark_path": "articles/watermark-1606739996مر.PNG",
        "width": 749
    },
    "post_date": "2020-11-30T14:23:00.000+03:00",
    "published": [
        {
            "id": "5faae9a3eb65480410630895",
            "link": "https://web.facebook.com/abderazak.73/posts/215106053383858",
            "name": "Ali Harizi",
            "origin": "",
            "path": "sources/af6f8f22c296a2f707be1985c48b9d0009cfa471.jpg"
        },
        {
            "id": "5fc4efd33e9c29111b3fcdc1",
            "link": "https://www.facebook.com/permalink.php?story_fbid=906535260154234&id=100023933043559",
            "name": "Said Said",
            "origin": "facebook",
            "path": "sources/190786e669cb726038cc75a272ae59bbe4cb9ed0.jpg"
        },
        {
            "id": "5fc4efd3cb0b2a62635867f8",
            "link": "https://www.facebook.com/TAWALT2/posts/193481862342961",
            "name": "Tawalt",
            "origin": "facebook",
            "path": "sources/0b702105071d7c4b132d074e46d14249e2f35102.jpg"
        }
    ],
    "result": "misleading",
    "shared_articles_count": 0,
    "sources": [
        {
            "id": "5f8edfb4148b827f7d192205",
            "link": "https://youtu.be/5hcVRpYCops",
            "name": "قناة يوتيوب",
            "origin": "",
            "path": "sources/f4e473f70061267e3fbe3df8d9498087e3cf99aa.jpg"
        },
        {
            "id": "5fc4f49f7b98ef77da524ba5",
            "link": "https://www.up.com/aboutup/corporate_info/uprrover/index.htm",
            "name": "Union Pacific",
            "origin": "",
            "path": "sources/2d646ea02f41545686a8e001610da110b6ce0eef.jpg"
        }
    ],
    "stats": null,
    "subtitle": "",
    "title": "الفيديو قديم ولا يُظهر معدات عسكرية مغربية في معبر الكركرات",
    "updated_at": "2020-11-30 17:18:18",
    "url_path": "/factcheck/2020/11/30/الفيديو-قديم-ولا-يظهر-معدات-عسكرية-مغربية-في-معبر-الكركرات",
    "was_notification_pushed": "true"
}